{
  "schemaVersion": 1,
  "id": "garpedans",
  "slug": "garpedans",
  "name": "Garpedans",
  "description": "Garpedansberget bjuder på mycket fin lodrät och överhängande klättring och är som högst 17 m högt. Det är klättring på mycket fast röd granit. Det finns flera leder med mycket hög kvalitet och som kräver god teknik och problemlösningsförmåga. Ett av Sveriges bästa berg i den typ av klättring som finns. En utmaning som absolut är värd att besöka om du klättrar i de övre svårighetsgraderna. Du har också en underbar utsikt över Gamlebyviken.",
  "coordinates": {
    "latitude": 57.90224,
    "longitude": 16.40421
  },
  "categories": [
    "mix",
    "Saknar skrivarformatering",
    "Saknar vägbeskrivning",
    "sport",
    "sva",
    "trad",
    "vertikalt",
    "överhäng"
  ],
  "sections": [
    {
      "id": "allmant",
      "title": "Allmänt",
      "body": "Garpedansberget bjuder på mycket fin lodrät och överhängande klättring och är som högst 17 m högt. Det är klättring på mycket fast röd granit. Det finns flera leder med mycket hög kvalitet och som kräver god teknik och problemlösningsförmåga. Ett av Sveriges bästa berg i den typ av klättring som finns. En utmaning som absolut är värd att besöka om du klättrar i de övre svårighetsgraderna. Du har också en underbar utsikt över Gamlebyviken."
    },
    {
      "id": "vagbeskrivning",
      "title": "Vägbeskrivning",
      "body": "Klippan ligger ca 25 km norr om Västervik. Kör av E22 den nordliga avfarten mot Gamleby och sedan ca 1 km förbi färgfabriken på vänster sida tills du kommer till en nedlagd bensinstation på höger sida. Parkera här och fortsätt att gå upp till vänster bland husen 300 m till berget som är väl synligt från vägen. Klippan är lättillgänglig och barnvänlig."
    },
    {
      "id": "ovrigt",
      "title": "Övrigt",
      "body": "I början av 90-talet klättrade Jim Wasmuth leden “Pieta” som först graderades till 7c. Den har kontinuerligt uppgraderats. Nu är den 8a+. Det var med all sannolikhet sveriges svåraste led då. Under 20 år efter förstabestigningen har den endast fått två repetitioner. Många duktiga klättrare har försökt. Väggen är vänd mot syd och får sol på sommaren efter ca kl.10.00. Den torkar relativt snabbt efter regn. Klippan har 11 leder som särskilt rekommenderas."
    },
    {
      "id": "overnattning",
      "title": "Övernattning",
      "body": "Camping finns på KustCamp vid Hammarsbadet lsom ligger 2 km sydost om Gamleby centrum tel 0493-10221 www.campa.se, Överums vandrarhem tel 0493-30302 www.overum.nu, stugor och camping har Risebo fritid, tel 0493-33046, www.risebofritid.se, camping och stugor finns på Lysingsbadet i Västervik tel 0490-258000 www.lysingsbadet.se, stugor har Tofvehults café och konferens tel 0490-26351 www.tofvehult.se och på Live in Nature på Kallersnäs gård tel 0768-513090 www.liveinnature.se"
    },
    {
      "id": "affarer",
      "title": "Affärer",
      "body": "Närmaste livsmedelsaffär ICA finns i Gamleby centrum 1 km från klippan. Närmaste bensinstation Bilia och Preem finns i Gamleby."
    },
    {
      "id": "klattercenter",
      "title": "Klättercenter",
      "body": "Mötesplatsen för klättrare är på centret i Västervik, Repslagargatan 5, vid gamla vattentornet. Där kan man koppla upp sig gratis på trådlöst internet, eller låna en dator. En plats att mötas på, utbyta erfarenheter, läsa klättertidningar, se klätterfilmer och även få aktuell information om klättringen och andra aktiviteter i kommunen. En plats där man kan klättra inomhus och lära känna andra klättrare. Ring 0490-37466 för mer information."
    },
    {
      "id": "forare",
      "title": "Förare",
      "body": ""
    }
  ],
  "routes": [
    {
      "id": "garpedans-led-1",
      "kind": "route",
      "number": "1",
      "name": "Dans dela garpe",
      "grade": "6b",
      "length": "10",
      "type": "sport",
      "firstAscent": "Johan Strömstad -89",
      "description": "kil led, 150 m till vänster",
      "sectorId": "forare",
      "source": {
        "id": "legacy:garpedans",
        "path": "mediawiki/Garpedans.txt"
      }
    },
    {
      "id": "garpedans-led-2",
      "kind": "route",
      "number": "2",
      "name": "Poga din ponkare",
      "grade": "7b",
      "length": "12",
      "type": "sport",
      "firstAscent": "Patrik Andersson -89",
      "description": "mixad led, till vänster",
      "sectorId": "forare",
      "source": {
        "id": "legacy:garpedans",
        "path": "mediawiki/Garpedans.txt"
      }
    },
    {
      "id": "garpedans-led-3",
      "kind": "route",
      "number": "3",
      "name": "Feta läppar",
      "grade": "6c+",
      "length": "10",
      "type": "sport",
      "firstAscent": "Patrik andersson -89",
      "description": "",
      "sectorId": "forare",
      "source": {
        "id": "legacy:garpedans",
        "path": "mediawiki/Garpedans.txt"
      }
    },
    {
      "id": "garpedans-led-4",
      "kind": "route",
      "number": "4",
      "name": "Flickan med kalejdoskopet",
      "grade": "6b",
      "length": "14",
      "type": "sport",
      "firstAscent": "Johan Hedkvist -89",
      "description": "",
      "sectorId": "forare",
      "source": {
        "id": "legacy:garpedans",
        "path": "mediawiki/Garpedans.txt"
      }
    },
    {
      "id": "garpedans-led-5",
      "kind": "route",
      "number": "5",
      "name": "Bolero",
      "grade": "6c",
      "length": "14",
      "type": "sport",
      "firstAscent": "Jim Wasmuth -89",
      "description": "",
      "sectorId": "forare",
      "source": {
        "id": "legacy:garpedans",
        "path": "mediawiki/Garpedans.txt"
      }
    },
    {
      "id": "garpedans-led-6",
      "kind": "route",
      "number": "6",
      "name": "Hammarhjärta",
      "grade": "6c",
      "length": "14",
      "type": "sport",
      "firstAscent": "Johan Hedkvist -89",
      "description": "kil led, orensad",
      "sectorId": "forare",
      "source": {
        "id": "legacy:garpedans",
        "path": "mediawiki/Garpedans.txt"
      }
    },
    {
      "id": "garpedans-led-7",
      "kind": "route",
      "number": "7",
      "name": "Bultat hjärta",
      "grade": "6c",
      "length": "14",
      "type": "sport",
      "firstAscent": "Jim Wasmuth -89",
      "description": "",
      "sectorId": "forare",
      "source": {
        "id": "legacy:garpedans",
        "path": "mediawiki/Garpedans.txt"
      }
    },
    {
      "id": "garpedans-led-8",
      "kind": "route",
      "number": "8",
      "name": "Sup dig snygg",
      "grade": "7a",
      "length": "15",
      "type": "sport",
      "firstAscent": "Patrik Andersson -90",
      "description": "",
      "sectorId": "forare",
      "source": {
        "id": "legacy:garpedans",
        "path": "mediawiki/Garpedans.txt"
      }
    },
    {
      "id": "garpedans-led-9",
      "kind": "route",
      "number": "9",
      "name": "Burton",
      "grade": "7b",
      "length": "14",
      "type": "sport",
      "firstAscent": "Jim Wasmuth -90",
      "description": "",
      "sectorId": "forare",
      "source": {
        "id": "legacy:garpedans",
        "path": "mediawiki/Garpedans.txt"
      }
    },
    {
      "id": "garpedans-led-10",
      "kind": "route",
      "number": "10",
      "name": "Blå grodorna",
      "grade": "7c",
      "length": "14",
      "type": "sport",
      "firstAscent": "Johan Luhr -02",
      "description": "",
      "sectorId": "forare",
      "source": {
        "id": "legacy:garpedans",
        "path": "mediawiki/Garpedans.txt"
      }
    },
    {
      "id": "garpedans-led-11",
      "kind": "route",
      "number": "11",
      "name": "Pieta",
      "grade": "8a+",
      "length": "15",
      "type": "sport",
      "firstAscent": "Jim Wasmuth -90",
      "description": "",
      "sectorId": "forare",
      "source": {
        "id": "legacy:garpedans",
        "path": "mediawiki/Garpedans.txt"
      }
    },
    {
      "id": "garpedans-led-12",
      "kind": "route",
      "number": "12",
      "name": "Rosa på bal",
      "grade": "7b+",
      "length": "15",
      "type": "sport",
      "firstAscent": "Patrik Andersson -90",
      "description": "",
      "sectorId": "forare",
      "source": {
        "id": "legacy:garpedans",
        "path": "mediawiki/Garpedans.txt"
      }
    },
    {
      "id": "garpedans-led-13",
      "kind": "route",
      "number": "13",
      "name": "Megadans",
      "grade": "7 b",
      "length": "15",
      "type": "sport",
      "firstAscent": "Patrik Andersson -90",
      "description": "",
      "sectorId": "forare",
      "source": {
        "id": "legacy:garpedans",
        "path": "mediawiki/Garpedans.txt"
      }
    },
    {
      "id": "garpedans-led-14",
      "kind": "route",
      "number": "14",
      "name": "Jolly",
      "grade": "6b",
      "length": "8",
      "type": "sport",
      "firstAscent": "Johan Luhr -01",
      "description": "",
      "sectorId": "forare",
      "source": {
        "id": "legacy:garpedans",
        "path": "mediawiki/Garpedans.txt"
      }
    },
    {
      "id": "garpedans-led-15",
      "kind": "route",
      "number": "15",
      "name": "Tejp",
      "grade": "6c",
      "length": "8",
      "type": "sport",
      "firstAscent": "Johan Luhr -01",
      "description": "",
      "sectorId": "forare",
      "source": {
        "id": "legacy:garpedans",
        "path": "mediawiki/Garpedans.txt"
      }
    },
    {
      "id": "garpedans-led-16",
      "kind": "route",
      "number": "16",
      "name": "Ge mig en grogg",
      "grade": "7b+",
      "length": "8",
      "type": "sport",
      "firstAscent": "Johan Luhr -03",
      "description": "",
      "sectorId": "forare",
      "source": {
        "id": "legacy:garpedans",
        "path": "mediawiki/Garpedans.txt"
      }
    },
    {
      "id": "garpedans-led-17",
      "kind": "route",
      "number": "17",
      "name": "Boys don´t cry",
      "grade": "7c",
      "length": "8",
      "type": "sport",
      "firstAscent": "Johan Luhr -00",
      "description": "",
      "sectorId": "forare",
      "source": {
        "id": "legacy:garpedans",
        "path": "mediawiki/Garpedans.txt"
      }
    },
    {
      "id": "garpedans-led-18",
      "kind": "route",
      "number": "18",
      "name": "Äventyrsklättraren",
      "grade": "6c",
      "length": "16",
      "type": "sport",
      "firstAscent": "Jim Wasmuth -89",
      "description": "kil led, orensad",
      "sectorId": "forare",
      "source": {
        "id": "legacy:garpedans",
        "path": "mediawiki/Garpedans.txt"
      }
    },
    {
      "id": "garpedans-led-19",
      "kind": "route",
      "number": "19",
      "name": "Mango tango",
      "grade": "7b",
      "length": "12",
      "type": "sport",
      "firstAscent": "Jim Wasmuth -89",
      "description": "",
      "sectorId": "forare",
      "source": {
        "id": "legacy:garpedans",
        "path": "mediawiki/Garpedans.txt"
      }
    },
    {
      "id": "garpedans-led-20",
      "kind": "route",
      "number": "20",
      "name": "Garpedansen",
      "grade": "6c",
      "length": "14",
      "type": "sport",
      "firstAscent": "Jim Wasmuth -89",
      "description": "ut till höger på hyllan",
      "sectorId": "forare",
      "source": {
        "id": "legacy:garpedans",
        "path": "mediawiki/Garpedans.txt"
      }
    },
    {
      "id": "garpedans-led-21",
      "kind": "route",
      "number": "21",
      "name": "Stone cold",
      "grade": "8a",
      "length": "10",
      "type": "sport",
      "firstAscent": "Johan Luhr -92",
      "description": "",
      "sectorId": "forare",
      "source": {
        "id": "legacy:garpedans",
        "path": "mediawiki/Garpedans.txt"
      }
    },
    {
      "id": "garpedans-led-22",
      "kind": "route",
      "number": "22",
      "name": "Flickorna i Småland",
      "grade": "7b",
      "length": "17",
      "type": "sport",
      "firstAscent": "Jim Wasmuth -89",
      "description": "en spännande pärla",
      "sectorId": "forare",
      "source": {
        "id": "legacy:garpedans",
        "path": "mediawiki/Garpedans.txt"
      }
    },
    {
      "id": "garpedans-led-23",
      "kind": "route",
      "number": "23",
      "name": "E66",
      "grade": "6c+",
      "length": "12",
      "type": "sport",
      "firstAscent": "Jim Wasmuth -89",
      "description": "",
      "sectorId": "forare",
      "source": {
        "id": "legacy:garpedans",
        "path": "mediawiki/Garpedans.txt"
      }
    },
    {
      "id": "garpedans-led-24",
      "kind": "route",
      "number": "24",
      "name": "Garpe diem",
      "grade": "7c",
      "length": "8",
      "type": "sport",
      "firstAscent": "Nicklas Enlund -07",
      "description": "",
      "sectorId": "forare",
      "source": {
        "id": "legacy:garpedans",
        "path": "mediawiki/Garpedans.txt"
      }
    },
    {
      "id": "garpedans-led-25",
      "kind": "route",
      "number": "25",
      "name": "Spin",
      "grade": "7a+",
      "length": "8",
      "type": "sport",
      "firstAscent": "Johan Luhr -03",
      "description": "ligger ca 250 m till höger",
      "sectorId": "forare",
      "source": {
        "id": "legacy:garpedans",
        "path": "mediawiki/Garpedans.txt"
      }
    },
    {
      "id": "garpedans-led-26",
      "kind": "route",
      "number": "26",
      "name": "Supra",
      "grade": "7b",
      "length": "6",
      "type": "sport",
      "firstAscent": "Johan Luhr -03",
      "description": "ligger ca 250 m till höger",
      "sectorId": "forare",
      "source": {
        "id": "legacy:garpedans",
        "path": "mediawiki/Garpedans.txt"
      }
    }
  ],
  "images": [
    {
      "filename": "Garpedans1.png",
      "caption": "Förare · foto",
      "missing": false,
      "sectorId": "forare",
      "routeIds": [
        "garpedans-led-1",
        "garpedans-led-2",
        "garpedans-led-3",
        "garpedans-led-4",
        "garpedans-led-5",
        "garpedans-led-6",
        "garpedans-led-7",
        "garpedans-led-8",
        "garpedans-led-9",
        "garpedans-led-10",
        "garpedans-led-11",
        "garpedans-led-12",
        "garpedans-led-13"
      ]
    },
    {
      "filename": "Garpedans2.png",
      "caption": "Förare · foto",
      "missing": false,
      "sectorId": "forare",
      "routeIds": [
        "garpedans-led-14",
        "garpedans-led-15",
        "garpedans-led-16",
        "garpedans-led-17",
        "garpedans-led-18",
        "garpedans-led-19",
        "garpedans-led-20",
        "garpedans-led-21",
        "garpedans-led-22",
        "garpedans-led-23",
        "garpedans-led-24",
        "garpedans-led-25",
        "garpedans-led-26"
      ]
    }
  ],
  "externalLinks": [
    {
      "url": "http://www.vastervikclimbing.se/klattercentret/pdfer/",
      "label": "www.vastervikclimbing.se",
      "sectionId": "forare"
    }
  ],
  "access": {
    "legacyText": null,
    "federationSlug": null
  },
  "qualityIssues": [],
  "provenance": {
    "primarySourceId": "legacy:garpedans",
    "sources": [
      {
        "id": "legacy:garpedans",
        "title": "Sverigeföraren 2014: Garpedans",
        "path": "mediawiki/Garpedans.txt",
        "license": "GNU Free Documentation License",
        "snapshotDate": "2014-01-01"
      }
    ]
  }
}
