{
  "schemaVersion": 1,
  "id": "nacka-sjukhus",
  "slug": "nacka-sjukhus",
  "name": "Nacka Sjukhus",
  "description": "http://www.klatterverket.se/bloc/sjukhus.html Vi har fått ok att lägga upp denna förare på Sverigeföraren.",
  "coordinates": null,
  "categories": [
    "Nacka-Värmdö",
    "Stockholm"
  ],
  "sections": [],
  "routes": [],
  "images": [],
  "externalLinks": [
    {
      "url": "http://www.klatterverket.se/bloc/sjukhus.html",
      "label": "sjukhus.html",
      "sectionId": null
    }
  ],
  "access": {
    "legacyText": null,
    "federationSlug": null
  },
  "qualityIssues": [],
  "provenance": {
    "primarySourceId": "legacy:nacka-sjukhus",
    "sources": [
      {
        "id": "legacy:nacka-sjukhus",
        "title": "Sverigeföraren 2014: Nacka Sjukhus",
        "path": "mediawiki/Nacka Sjukhus.txt",
        "license": "GNU Free Documentation License",
        "snapshotDate": "2014-01-01"
      }
    ]
  }
}
